{
  "stats": {
    "suites": 3,
    "tests": 20,
    "passes": 19,
    "pending": 0,
    "failures": 1,
    "testsRegistered": 20,
    "passPercent": 95,
    "pendingPercent": 0,
    "other": 0,
    "hasOther": false,
    "skipped": 0,
    "hasSkipped": false,
    "start": "2025-12-14T16:33:22.884Z",
    "end": "2025-12-14T16:35:25.525Z",
    "duration": 122641
  },
  "results": [
    {
      "uuid": "c3c5227c-b4c8-4ca4-8150-6913219376c4",
      "title": "",
      "fullFile": "cypress/e2e/runBeforeAll/index.spec.js",
      "file": "cypress/e2e/runBeforeAll/index.spec.js",
      "beforeHooks": [],
      "afterHooks": [],
      "tests": [],
      "suites": [
        {
          "uuid": "547feede-e247-493f-bcc7-533ec0af0b59",
          "title": "E2E tests 2025-12-14 17:33:22 Stockholm time zone",
          "fullFile": "",
          "file": "",
          "beforeHooks": [],
          "afterHooks": [],
          "tests": [
            {
              "title": "Initiate common state",
              "fullTitle": "E2E tests 2025-12-14 17:33:22 Stockholm time zone Initiate common state",
              "timedOut": null,
              "duration": 72,
              "state": "passed",
              "speed": "fast",
              "pass": true,
              "fail": false,
              "pending": false,
              "context": null,
              "code": "cy.writeFile('cypress/fixtures/commonState.json', JSON.stringify(_constants.commonState));",
              "err": {},
              "uuid": "58572a3c-4e82-42d2-86ad-987d09b4630c",
              "parentUUID": "547feede-e247-493f-bcc7-533ec0af0b59",
              "isHook": false,
              "skipped": false
            }
          ],
          "suites": [],
          "passes": [
            "58572a3c-4e82-42d2-86ad-987d09b4630c"
          ],
          "failures": [],
          "pending": [],
          "skipped": [],
          "duration": 72,
          "root": false,
          "rootEmpty": false,
          "_timeout": 2000
        }
      ],
      "passes": [],
      "failures": [],
      "pending": [],
      "skipped": [],
      "duration": 0,
      "root": true,
      "rootEmpty": true,
      "_timeout": 2000
    },
    {
      "uuid": "8a8a26a9-325e-4732-9a5f-f4e3f5ae2155",
      "title": "",
      "fullFile": "cypress/e2e/contexts/about/run_Verify_Page.spec.js",
      "file": "cypress/e2e/contexts/about/run_Verify_Page.spec.js",
      "beforeHooks": [],
      "afterHooks": [],
      "tests": [],
      "suites": [
        {
          "uuid": "600ddfe5-8468-4673-933d-c83c5dcc0fd1",
          "title": "Verify about page content",
          "fullFile": "",
          "file": "",
          "beforeHooks": [],
          "afterHooks": [],
          "tests": [],
          "suites": [
            {
              "uuid": "276a79e4-a120-4ef6-a4f9-388cd08fad13",
              "title": "Tests",
              "fullFile": "",
              "file": "",
              "beforeHooks": [],
              "afterHooks": [],
              "tests": [],
              "suites": [
                {
                  "uuid": "4fad9e77-ed6c-4bf5-b0eb-85e6280e1a06",
                  "title": "Verify",
                  "fullFile": "",
                  "file": "",
                  "beforeHooks": [],
                  "afterHooks": [],
                  "tests": [
                    {
                      "title": "When I go to about page",
                      "fullTitle": "Verify about page content Tests Verify When I go to about page",
                      "timedOut": null,
                      "duration": 1713,
                      "state": "passed",
                      "speed": "fast",
                      "pass": true,
                      "fail": false,
                      "pending": false,
                      "context": null,
                      "code": "cy.visit('/about');",
                      "err": {},
                      "uuid": "5285c1ed-87cf-44b8-b94f-cb329df18fd1",
                      "parentUUID": "4fad9e77-ed6c-4bf5-b0eb-85e6280e1a06",
                      "isHook": false,
                      "skipped": false
                    },
                    {
                      "title": "Then I verify about content",
                      "fullTitle": "Verify about page content Tests Verify Then I verify about content",
                      "timedOut": null,
                      "duration": 71,
                      "state": "passed",
                      "speed": "fast",
                      "pass": true,
                      "fail": false,
                      "pending": false,
                      "context": null,
                      "code": "_about.default.verifyAbout({\n  header: _about2.default.about.header,\n  aboutText: _about2.default.about.text\n});",
                      "err": {},
                      "uuid": "ae371195-ec14-4348-9f00-f41cf8c2b83a",
                      "parentUUID": "4fad9e77-ed6c-4bf5-b0eb-85e6280e1a06",
                      "isHook": false,
                      "skipped": false
                    },
                    {
                      "title": "Then I verify first expertise",
                      "fullTitle": "Verify about page content Tests Verify Then I verify first expertise",
                      "timedOut": null,
                      "duration": 40,
                      "state": "passed",
                      "speed": "fast",
                      "pass": true,
                      "fail": false,
                      "pending": false,
                      "context": null,
                      "code": "_about.default.verifyExpertise({\n  header: _about2.default.expertise.header,\n  expertise: _about2.default.expertise.expertise_1\n});",
                      "err": {},
                      "uuid": "27008e9a-bac2-4a81-95c3-ea9579da7dc1",
                      "parentUUID": "4fad9e77-ed6c-4bf5-b0eb-85e6280e1a06",
                      "isHook": false,
                      "skipped": false
                    },
                    {
                      "title": "Then I verify second expertise",
                      "fullTitle": "Verify about page content Tests Verify Then I verify second expertise",
                      "timedOut": null,
                      "duration": 43,
                      "state": "passed",
                      "speed": "fast",
                      "pass": true,
                      "fail": false,
                      "pending": false,
                      "context": null,
                      "code": "_about.default.verifyExpertise({\n  header: _about2.default.expertise.header,\n  expertise: _about2.default.expertise.expertise_2\n});",
                      "err": {},
                      "uuid": "25166059-be95-4dae-9df9-5ccbf2e73211",
                      "parentUUID": "4fad9e77-ed6c-4bf5-b0eb-85e6280e1a06",
                      "isHook": false,
                      "skipped": false
                    },
                    {
                      "title": "Then I verify third expertise",
                      "fullTitle": "Verify about page content Tests Verify Then I verify third expertise",
                      "timedOut": null,
                      "duration": 36,
                      "state": "passed",
                      "speed": "fast",
                      "pass": true,
                      "fail": false,
                      "pending": false,
                      "context": null,
                      "code": "_about.default.verifyExpertise({\n  header: _about2.default.expertise.header,\n  expertise: _about2.default.expertise.expertise_3\n});",
                      "err": {},
                      "uuid": "f34b8ecf-7119-483b-8dd1-d8b37fdfd8cd",
                      "parentUUID": "4fad9e77-ed6c-4bf5-b0eb-85e6280e1a06",
                      "isHook": false,
                      "skipped": false
                    },
                    {
                      "title": "Then I verify fourth expertise",
                      "fullTitle": "Verify about page content Tests Verify Then I verify fourth expertise",
                      "timedOut": null,
                      "duration": 38,
                      "state": "passed",
                      "speed": "fast",
                      "pass": true,
                      "fail": false,
                      "pending": false,
                      "context": null,
                      "code": "_about.default.verifyExpertise({\n  header: _about2.default.expertise.header,\n  expertise: _about2.default.expertise.expertise_4\n});",
                      "err": {},
                      "uuid": "4b31340f-030b-41f6-be13-512aac2a1e0c",
                      "parentUUID": "4fad9e77-ed6c-4bf5-b0eb-85e6280e1a06",
                      "isHook": false,
                      "skipped": false
                    },
                    {
                      "title": "Then I verify fifth expertise",
                      "fullTitle": "Verify about page content Tests Verify Then I verify fifth expertise",
                      "timedOut": null,
                      "duration": 45,
                      "state": "passed",
                      "speed": "fast",
                      "pass": true,
                      "fail": false,
                      "pending": false,
                      "context": null,
                      "code": "_about.default.verifyExpertise({\n  header: _about2.default.expertise.header,\n  expertise: _about2.default.expertise.expertise_5\n});",
                      "err": {},
                      "uuid": "3d1cf463-728e-4563-81c6-bbd80271bc07",
                      "parentUUID": "4fad9e77-ed6c-4bf5-b0eb-85e6280e1a06",
                      "isHook": false,
                      "skipped": false
                    },
                    {
                      "title": "Then I verify sixth expertise",
                      "fullTitle": "Verify about page content Tests Verify Then I verify sixth expertise",
                      "timedOut": null,
                      "duration": 41,
                      "state": "passed",
                      "speed": "fast",
                      "pass": true,
                      "fail": false,
                      "pending": false,
                      "context": null,
                      "code": "_about.default.verifyExpertise({\n  header: _about2.default.expertise.header,\n  expertise: _about2.default.expertise.expertise_6\n});",
                      "err": {},
                      "uuid": "055558e9-2169-45e5-b4ff-d3b41ba5ba27",
                      "parentUUID": "4fad9e77-ed6c-4bf5-b0eb-85e6280e1a06",
                      "isHook": false,
                      "skipped": false
                    }
                  ],
                  "suites": [],
                  "passes": [
                    "5285c1ed-87cf-44b8-b94f-cb329df18fd1",
                    "ae371195-ec14-4348-9f00-f41cf8c2b83a",
                    "27008e9a-bac2-4a81-95c3-ea9579da7dc1",
                    "25166059-be95-4dae-9df9-5ccbf2e73211",
                    "f34b8ecf-7119-483b-8dd1-d8b37fdfd8cd",
                    "4b31340f-030b-41f6-be13-512aac2a1e0c",
                    "3d1cf463-728e-4563-81c6-bbd80271bc07",
                    "055558e9-2169-45e5-b4ff-d3b41ba5ba27"
                  ],
                  "failures": [],
                  "pending": [],
                  "skipped": [],
                  "duration": 2027,
                  "root": false,
                  "rootEmpty": false,
                  "_timeout": 2000
                }
              ],
              "passes": [],
              "failures": [],
              "pending": [],
              "skipped": [],
              "duration": 0,
              "root": false,
              "rootEmpty": false,
              "_timeout": 2000
            }
          ],
          "passes": [],
          "failures": [],
          "pending": [],
          "skipped": [],
          "duration": 0,
          "root": false,
          "rootEmpty": false,
          "_timeout": 2000
        }
      ],
      "passes": [],
      "failures": [],
      "pending": [],
      "skipped": [],
      "duration": 0,
      "root": true,
      "rootEmpty": true,
      "_timeout": 2000
    },
    {
      "uuid": "6a2acb6d-0d65-4cb5-bdd0-7e94ae6ff49c",
      "title": "",
      "fullFile": "cypress/e2e/contexts/home/run_Verify_Page.spec.js",
      "file": "cypress/e2e/contexts/home/run_Verify_Page.spec.js",
      "beforeHooks": [],
      "afterHooks": [],
      "tests": [],
      "suites": [
        {
          "uuid": "1166a555-b6e9-4032-9dd5-d7eac3ff073e",
          "title": "Verify home page content",
          "fullFile": "",
          "file": "",
          "beforeHooks": [],
          "afterHooks": [],
          "tests": [],
          "suites": [
            {
              "uuid": "b55d35ae-cd08-4e68-8a7e-f3c70c808efa",
              "title": "Tests",
              "fullFile": "",
              "file": "",
              "beforeHooks": [],
              "afterHooks": [],
              "tests": [],
              "suites": [
                {
                  "uuid": "15b7a3fe-87ae-47d6-9b48-11e15356a85e",
                  "title": "Verify",
                  "fullFile": "",
                  "file": "",
                  "beforeHooks": [],
                  "afterHooks": [],
                  "tests": [
                    {
                      "title": "When I go to home page",
                      "fullTitle": "Verify home page content Tests Verify When I go to home page",
                      "timedOut": null,
                      "duration": 1081,
                      "state": "passed",
                      "speed": "fast",
                      "pass": true,
                      "fail": false,
                      "pending": false,
                      "context": null,
                      "code": "cy.visit('/');",
                      "err": {},
                      "uuid": "ca1754f7-529e-40e8-895b-7f40e2a43e05",
                      "parentUUID": "15b7a3fe-87ae-47d6-9b48-11e15356a85e",
                      "isHook": false,
                      "skipped": false
                    },
                    {
                      "title": "Then I verify home welcome content",
                      "fullTitle": "Verify home page content Tests Verify Then I verify home welcome content",
                      "timedOut": null,
                      "duration": 88,
                      "state": "passed",
                      "speed": "fast",
                      "pass": true,
                      "fail": false,
                      "pending": false,
                      "context": null,
                      "code": "_home.default.verifyHome({\n  header: _home2.default.home.header,\n  homeText: _home2.default.home.text\n});",
                      "err": {},
                      "uuid": "2c2d834d-d4b9-4815-bc52-bff7c54c9e2e",
                      "parentUUID": "15b7a3fe-87ae-47d6-9b48-11e15356a85e",
                      "isHook": false,
                      "skipped": false
                    },
                    {
                      "title": "Then I verify first post",
                      "fullTitle": "Verify home page content Tests Verify Then I verify first post",
                      "timedOut": null,
                      "duration": 669,
                      "state": "passed",
                      "speed": "fast",
                      "pass": true,
                      "fail": false,
                      "pending": false,
                      "context": null,
                      "code": "_home.default.verifyPosts({\n  header: _home2.default.posts.header,\n  article: _home2.default.posts.article_1\n});",
                      "err": {},
                      "uuid": "bdd0a083-9bfa-4a14-bab8-a83b9ae5a487",
                      "parentUUID": "15b7a3fe-87ae-47d6-9b48-11e15356a85e",
                      "isHook": false,
                      "skipped": false
                    },
                    {
                      "title": "Then I verify second post",
                      "fullTitle": "Verify home page content Tests Verify Then I verify second post",
                      "timedOut": null,
                      "duration": 931,
                      "state": "passed",
                      "speed": "fast",
                      "pass": true,
                      "fail": false,
                      "pending": false,
                      "context": null,
                      "code": "_home.default.verifyPosts({\n  header: _home2.default.posts.header,\n  article: _home2.default.posts.article_2\n});",
                      "err": {},
                      "uuid": "14e2eae7-0e74-40d7-9b87-6deae30c64f0",
                      "parentUUID": "15b7a3fe-87ae-47d6-9b48-11e15356a85e",
                      "isHook": false,
                      "skipped": false
                    },
                    {
                      "title": "Then I verify third post",
                      "fullTitle": "Verify home page content Tests Verify Then I verify third post",
                      "timedOut": null,
                      "duration": 558,
                      "state": "passed",
                      "speed": "fast",
                      "pass": true,
                      "fail": false,
                      "pending": false,
                      "context": null,
                      "code": "_home.default.verifyPosts({\n  header: _home2.default.posts.header,\n  article: _home2.default.posts.article_3\n});",
                      "err": {},
                      "uuid": "c63618fa-0151-43f0-8f53-042b2f9c2528",
                      "parentUUID": "15b7a3fe-87ae-47d6-9b48-11e15356a85e",
                      "isHook": false,
                      "skipped": false
                    },
                    {
                      "title": "Then I verify fourth post",
                      "fullTitle": "Verify home page content Tests Verify Then I verify fourth post",
                      "timedOut": null,
                      "duration": 475,
                      "state": "passed",
                      "speed": "fast",
                      "pass": true,
                      "fail": false,
                      "pending": false,
                      "context": null,
                      "code": "_home.default.verifyPosts({\n  header: _home2.default.posts.header,\n  article: _home2.default.posts.article_4\n});",
                      "err": {},
                      "uuid": "e835e2e6-8699-4cf0-8934-a9790d2126bd",
                      "parentUUID": "15b7a3fe-87ae-47d6-9b48-11e15356a85e",
                      "isHook": false,
                      "skipped": false
                    },
                    {
                      "title": "Then I verify fifth post and navigate to next page",
                      "fullTitle": "Verify home page content Tests Verify Then I verify fifth post and navigate to next page",
                      "timedOut": null,
                      "duration": 729,
                      "state": "passed",
                      "speed": "fast",
                      "pass": true,
                      "fail": false,
                      "pending": false,
                      "context": null,
                      "code": "_home.default.verifyPosts({\n  header: _home2.default.posts.header,\n  article: _home2.default.posts.article_5,\n  changePage: 'Next'\n});",
                      "err": {},
                      "uuid": "3d477fab-d1f5-440b-80da-fa9d9d6536fc",
                      "parentUUID": "15b7a3fe-87ae-47d6-9b48-11e15356a85e",
                      "isHook": false,
                      "skipped": false
                    },
                    {
                      "title": "Then I verify sixth post",
                      "fullTitle": "Verify home page content Tests Verify Then I verify sixth post",
                      "timedOut": null,
                      "duration": 421,
                      "state": "passed",
                      "speed": "fast",
                      "pass": true,
                      "fail": false,
                      "pending": false,
                      "context": null,
                      "code": "_home.default.verifyPosts({\n  header: _home2.default.posts.header,\n  article: _home2.default.posts.article_6\n});",
                      "err": {},
                      "uuid": "9e1b3c4d-fdca-4116-903d-980e478cd9c3",
                      "parentUUID": "15b7a3fe-87ae-47d6-9b48-11e15356a85e",
                      "isHook": false,
                      "skipped": false
                    },
                    {
                      "title": "Then I verify seventh post",
                      "fullTitle": "Verify home page content Tests Verify Then I verify seventh post",
                      "timedOut": null,
                      "duration": 268,
                      "state": "passed",
                      "speed": "fast",
                      "pass": true,
                      "fail": false,
                      "pending": false,
                      "context": null,
                      "code": "_home.default.verifyPosts({\n  header: _home2.default.posts.header,\n  article: _home2.default.posts.article_7\n});",
                      "err": {},
                      "uuid": "efc9d6d9-360f-4da0-9905-0879b9f2e991",
                      "parentUUID": "15b7a3fe-87ae-47d6-9b48-11e15356a85e",
                      "isHook": false,
                      "skipped": false
                    },
                    {
                      "title": "Then I verify eighth post",
                      "fullTitle": "Verify home page content Tests Verify Then I verify eighth post",
                      "timedOut": null,
                      "duration": 250,
                      "state": "passed",
                      "speed": "fast",
                      "pass": true,
                      "fail": false,
                      "pending": false,
                      "context": null,
                      "code": "_home.default.verifyPosts({\n  header: _home2.default.posts.header,\n  article: _home2.default.posts.article_8\n});",
                      "err": {},
                      "uuid": "4eb5f9b8-9276-49cc-b9d7-9e70e4801f4c",
                      "parentUUID": "15b7a3fe-87ae-47d6-9b48-11e15356a85e",
                      "isHook": false,
                      "skipped": false
                    },
                    {
                      "title": "Then I verify ninth post and navigate to previous page",
                      "fullTitle": "Verify home page content Tests Verify Then I verify ninth post and navigate to previous page",
                      "timedOut": null,
                      "duration": 20226,
                      "state": "failed",
                      "speed": null,
                      "pass": false,
                      "fail": true,
                      "pending": false,
                      "context": "[\n  \"assets/run_Verify_Page/Then I verify ninth post and navigate to previous page.png\",\n  \"Timestamp: 2025-12-14 17:35:19 Stockholm time zone\",\n  \"Timestamp: 2025-12-14 16:35:19 UTC zone\"\n]",
                      "code": "_home.default.verifyPosts({\n  header: _home2.default.posts.header,\n  article: _home2.default.posts.article_9,\n  changePage: 'Previous'\n});",
                      "err": {
                        "message": "AssertionError: Timed out retrying after 20000ms: Expected to find content: 'WHAT IS TEST AUTOMATIONp' within the element: <h3> but never did.",
                        "estack": "AssertionError: Timed out retrying after 20000ms: Expected to find content: 'WHAT IS TEST AUTOMATIONp' within the element: <h3> but never did.\n    at Context.eval (webpack://cypress_e2e_my_blog/./cypress/e2e/pageObjects/home.js:23:40)\n    at getRet (https://tarlanziyadov.github.io/__cypress/runner/cypress_runner.js:122460:20)\n    at tryCatcher (https://tarlanziyadov.github.io/__cypress/runner/cypress_runner.js:1777:23)\n    at Promise.attempt.Promise.try (https://tarlanziyadov.github.io/__cypress/runner/cypress_runner.js:4285:29)\n    at Context.thenFn (https://tarlanziyadov.github.io/__cypress/runner/cypress_runner.js:122471:66)\n    at Context.then (https://tarlanziyadov.github.io/__cypress/runner/cypress_runner.js:122722:21)\n    at wrapped (https://tarlanziyadov.github.io/__cypress/runner/cypress_runner.js:145818:19)",
                        "diff": null
                      },
                      "uuid": "d64256f2-8296-40dc-a6be-661043226c42",
                      "parentUUID": "15b7a3fe-87ae-47d6-9b48-11e15356a85e",
                      "isHook": false,
                      "skipped": false
                    }
                  ],
                  "suites": [],
                  "passes": [
                    "ca1754f7-529e-40e8-895b-7f40e2a43e05",
                    "2c2d834d-d4b9-4815-bc52-bff7c54c9e2e",
                    "bdd0a083-9bfa-4a14-bab8-a83b9ae5a487",
                    "14e2eae7-0e74-40d7-9b87-6deae30c64f0",
                    "c63618fa-0151-43f0-8f53-042b2f9c2528",
                    "e835e2e6-8699-4cf0-8934-a9790d2126bd",
                    "3d477fab-d1f5-440b-80da-fa9d9d6536fc",
                    "9e1b3c4d-fdca-4116-903d-980e478cd9c3",
                    "efc9d6d9-360f-4da0-9905-0879b9f2e991",
                    "4eb5f9b8-9276-49cc-b9d7-9e70e4801f4c"
                  ],
                  "failures": [
                    "d64256f2-8296-40dc-a6be-661043226c42"
                  ],
                  "pending": [],
                  "skipped": [],
                  "duration": 25696,
                  "root": false,
                  "rootEmpty": false,
                  "_timeout": 2000
                }
              ],
              "passes": [],
              "failures": [],
              "pending": [],
              "skipped": [],
              "duration": 0,
              "root": false,
              "rootEmpty": false,
              "_timeout": 2000
            }
          ],
          "passes": [],
          "failures": [],
          "pending": [],
          "skipped": [],
          "duration": 0,
          "root": false,
          "rootEmpty": false,
          "_timeout": 2000
        }
      ],
      "passes": [],
      "failures": [],
      "pending": [],
      "skipped": [],
      "duration": 0,
      "root": true,
      "rootEmpty": true,
      "_timeout": 2000
    }
  ],
  "meta": {
    "mocha": {
      "version": "7.2.0"
    },
    "mochawesome": {
      "options": {
        "quiet": false,
        "reportFilename": "mochawesome",
        "saveHtml": false,
        "saveJson": true,
        "consoleReporter": "spec",
        "useInlineDiffs": false,
        "code": true
      },
      "version": "7.1.4"
    },
    "marge": {
      "options": {
        "reportDir": "cypress/reports/mocha",
        "charts": true,
        "overwrite": false,
        "reportPageTitle": "TarlanZiyadov_CypressE2E",
        "embeddedScreenshots": true,
        "inlineAssets": true,
        "saveAllAttempts": false,
        "showPassed": true,
        "showFailed": true,
        "showPending": true,
        "showSkipped": true,
        "html": false,
        "json": true
      },
      "version": "6.3.2"
    }
  }
}